{
  "afkzone": "afkzone",
  "arabicfixerpe": "arabicfixerpe",
  "autosellpe": "autosellpe",
  "badwordblocker": "badwordblocker",
  "bedwarspm": "bedwarspm",
  "deathchest": "deathchest",
  "fancygenerators": "fancygenerators",
  "ffa": "ffa",
  "friendsx": "friendsx",
  "hotblock": "hotblock",
  "martianenchantments": "martianenchantments",
  "perworldinventory": "perworldinventory",
  "root-emojis": "root-emojis",
  "simpleeconomy": "simpleeconomy",
  "superiorveinminer": "superiorveinminer",
  "topstats": "topstats",
  "uncensoraz": "uncensoraz",
  "vanillaweather": "vanillaweather",
  "visibleautopickup": "visibleautopickup",
  "worldguardplugin": "worldguardplugin",
  "worlds": "worlds",
  "wsrcon": "wsrcon",
  "xgtshowplayerhp": "xgtshowplayerhp",
  "xgtsmithingtable": "xgtsmithingtable",
  "_newalias": "newalias",
  "allsigns": "allsigns",
  "autoclearchunk": "autoclearchunk",
  "banknote": "banknote",
  "battlesense": "battlesense",
  "betteritemid": "betteritemid",
  "betternpc": "betternpc",
  "betterrewards": "betterrewards",
  "blockpets": "blockpets",
  "broadcastacm": "broadcastacm",
  "clearlagg": "clearlagg",
  "commandcooldown": "commandcooldown",
  "customgui": "customgui",
  "deathinventorylog": "deathinventorylog",
  "eastereggs": "eastereggs",
  "enderchest": "enderchest",
  "fireworkshow": "fireworkshow",
  "fixbucketitem": "fixbucketitem",
  "giveall": "giveall",
  "groupsystem": "groupsystem",
  "hidecommands": "hidecommands",
  "hiveorerewards": "hiveorerewards",
  "invcraft": "invcraft",
  "invsee": "invsee",
  "joinacm": "joinacm",
  "leaffooddrops": "leaffooddrops",
  "leap": "leap",
  "lifesteal": "lifesteal",
  "lmao": "lmao",
  "lootprotection": "lootprotection",
  "lytraffa": "lytraffa",
  "magicchest": "magicchest",
  "magmadamage": "magmadamage",
  "phpmailer": "phpmailer",
  "maskui": "maskui",
  "motdshuffle": "motdshuffle",
  "multiworld": "multiworld",
  "nethermenus": "nethermenus",
  "netherperms": "netherperms",
  "onjoin": "onjoin",
  "pausescreenping": "pausescreenping",
  "pearlmotion": "pearlmotion",
  "persianchatfixer": "persianchatfixer",
  "placeholderapi": "placeholderapi",
  "playercollide": "playercollide",
  "playerwarn": "playerwarn",
  "pmmp-ai": "pmmp-ai",
  "prismghostblock": "prismghostblock",
  "properduels": "properduels",
  "ranksystem": "ranksystem",
  "recon": "recon",
  "repairui": "repairui",
  "gamereplay": "gamereplay",
  "servercleaner": "servercleaner",
  "sizeui": "sizeui",
  "smaccer": "smaccer",
  "teleportto": "teleportto",
  "texter": "texter",
  "waypoint": "waypoint",
  "worldmanager": "worldmanager",
  "xzaffinity": "xzaffinity",
  "zfactions": "zfactions",
  "actionhouse": "actionhouse",
  "afksystem": "afksystem",
  "announcer": "announcer",
  "antialtaccounts": "antialtaccounts",
  "banknotesplus": "banknotesplus",
  "bansystem": "bansystem",
  "bettercoinflip": "bettercoinflip",
  "betterhub": "betterhub",
  "betternick": "betternick",
  "borderlimitpe": "borderlimitpe",
  "bowhitsound": "bowhitsound",
  "calculatorui": "calculatorui",
  "chalkboard": "chalkboard",
  "chatemojis": "chatemojis",
  "chatperms": "chatperms",
  "chattags": "chattags",
  "chunkborders": "chunkborders",
  "claimandprotect": "claimandprotect",
  "classicoregen": "classicoregen",
  "collisionboxesdrawer": "collisionboxesdrawer",
  "customies": "customies",
  "customsetting": "customsetting",
  "deathsign": "deathsign",
  "deluxecoinflip": "deluxecoinflip",
  "deluxeveinminer": "deluxeveinminer",
  "economyenchant": "economyenchant",
  "enderkits": "enderkits",
  "fakeop": "fakeop",
  "fireball": "fireball",
  "fps": "fps",
  "gminventories": "gminventories",
  "inputpermission": "inputpermission",
  "itemdurability": "itemdurability",
  "itemeditor": "itemeditor",
  "itemstacker": "itemstacker",
  "kitsystem": "kitsystem",
  "knockback": "knockback",
  "legacyachievements": "legacyachievements",
  "macepm": "macepm",
  "martianlootbox": "martianlootbox",
  "mentionitem": "mentionitem",
  "mineralgui": "mineralgui",
  "mtrim": "mtrim",
  "nightpvp": "nightpvp",
  "noitemenchant": "noitemenchant",
  "pchat": "pchat",
  "pets": "pets",
  "pocketblood": "pocketblood",
  "devtools": "devtools",
  "prefixes": "prefixes",
  "proban": "proban",
  "rcaptcha": "rcaptcha",
  "reachlimiter": "reachlimiter",
  "relicspe": "relicspe",
  "roulette": "roulette",
  "simpleclothes": "simpleclothes",
  "simplegift": "simplegift",
  "soulwell": "soulwell",
  "deathspectator": "deathspectator",
  "streakapi": "streakapi",
  "supplydrops": "supplydrops",
  "surrealffa": "surrealffa",
  "tntblastradius": "tntblastradius",
  "tokensapi": "tokensapi",
  "tridentpm": "tridentpm",
  "unicodesapi": "unicodesapi",
  "vanillafishing": "vanillafishing",
  "vanishv2": "vanishv2",
  "vibrantvisuals": "vibrantvisuals",
  "wdinventories": "wdinventories",
  "wdpepmtransfer": "wdpepmtransfer",
  "welcomemessages": "welcomemessages",
  "worldtimes": "worldtimes",
  "xpluginloader": "xpluginloader",
  "zuri": "zuri",
  "advancedareas": "advancedareas",
  "amazingdailys": "amazingdailys",
  "amazingsell": "amazingsell",
  "anvils": "anvils",
  "autofarmtools": "autofarmtools",
  "azusarealtime": "azusarealtime",
  "azusawordscramble": "azusawordscramble",
  "betterstaff": "betterstaff",
  "betterwardrobe": "betterwardrobe",
  "blockannouncer": "blockannouncer",
  "breakhearts": "breakhearts",
  "bridgeblockfix": "bridgeblockfix",
  "casino": "casino",
  "chatcensored": "chatcensored",
  "chatpings": "chatpings",
  "chatpm_gpt": "chatpm-gpt",
  "chestkitpro": "chestkitpro",
  "advancedcombat": "advancedcombat",
  "craft-remover": "craft-remover",
  "crashannouncer": "crashannouncer",
  "customareas": "customareas",
  "customflyspeed": "customflyspeed",
  "customrankjoinmessage": "customrankjoinmessage",
  "debugworld": "debugworld",
  "discordauth": "discordauth",
  "doubledoors": "doubledoors",
  "doubleslabs": "doubleslabs",
  "dynamicmotd": "dynamicmotd",
  "imagesloader": "imagesloader",
  "kdr-pe": "kdr-pe",
  "kingofthehill": "kingofthehill",
  "langmanager": "langmanager",
  "lavasell": "lavasell",
  "linkplayerscounter": "linkplayerscounter",
  "lumberjack": "lumberjack",
  "magiccrates": "magiccrates",
  "mailsystem": "mailsystem",
  "martianemotes": "martianemotes",
  "mcrates": "mcrates",
  "milestone": "milestone",
  "mineshop": "mineshop",
  "nodrops": "nodrops",
  "parachuteplus": "parachuteplus",
  "permissioneffects": "permissioneffects",
  "playersize": "playersize",
  "playertitles": "playertitles",
  "quicklyenchantments": "quicklyenchantments",
  "rpencrypter": "rpencrypter",
  "sell": "sell",
  "servercensored": "servercensored",
  "simpleping": "simpleping",
  "skillmastery": "skillmastery",
  "skinguard": "skinguard",
  "systemcps": "systemcps",
  "thechestlock": "thechestlock",
  "times": "times",
  "trampoline": "trampoline",
  "trickortreat": "trickortreat",
  "trollxd": "trollxd",
  "ultimatecaptcha": "ultimatecaptcha",
  "ultimatevote": "ultimatevote",
  "vorespawner": "vorespawner",
  "welcomemessage": "welcomemessage",
  "adaptivegc": "adaptivegc",
  "advancedsudo": "advancedsudo",
  "alwayseffect": "alwayseffect",
  "alwaystime": "alwaystime",
  "antistuck": "antistuck",
  "autobroadcast": "autobroadcast",
  "azusabanitem": "azusabanitem",
  "azusacoordinates": "azusacoordinates",
  "azusamath": "azusamath",
  "azusamute": "azusamute",
  "azusanametag": "azusanametag",
  "azusanightvision": "azusanightvision",
  "betterbrag": "betterbrag",
  "betterprisons": "betterprisons",
  "calculator": "calculator",
  "chatmath": "chatmath",
  "dancefarm": "dancefarm",
  "deviceacm": "deviceacm",
  "discordbot": "discordbot",
  "discordcontrolpanel": "discordcontrolpanel",
  "dogify": "dogify",
  "doubleslabbreaker": "doubleslabbreaker",
  "emptychunkremover": "emptychunkremover",
  "fallingtree": "fallingtree",
  "fastleafdecay": "fastleafdecay",
  "fly": "fly",
  "frost-football": "frost-football",
  "frostprofanityfilter": "frostprofanityfilter",
  "frosttictactoe": "frosttictactoe",
  "giftcode": "giftcode",
  "guardian": "guardian",
  "jailx": "jailx",
  "jumppad": "jumppad",
  "kxlootbox": "kxlootbox",
  "mapvideo": "mapvideo",
  "mineearn": "mineearn",
  "mobmorph": "mobmorph",
  "myitem": "myitem",
  "mynotes": "mynotes",
  "mytime": "mytime",
  "nofoodpm": "nofoodpm",
  "perworldchunktick": "perworldchunktick",
  "perworldviewdistance": "perworldviewdistance",
  "playerslist": "playerslist",
  "pmmpkahoot": "pmmpkahoot",
  "pockettranslate": "pockettranslate",
  "portals": "portals",
  "replantingcrops": "replantingcrops",
  "reportplayer": "reportplayer",
  "savedinventoryplayer": "savedinventoryplayer",
  "showcoordinates": "showcoordinates",
  "simpleoffhand": "simpleoffhand",
  "smoothpearl": "smoothpearl",
  "switching": "switching",
  "vbackpack": "vbackpack",
  "votingsleep": "votingsleep",
  "warpgui": "warpgui",
  "waterlogging": "waterlogging",
  "wavyantivoid": "wavyantivoid",
  "world-worker": "world-worker",
  "xgtnetheriteupgrade": "xgtnetheriteupgrade",
  "antivpn": "antivpn",
  "aquacrates": "aquacrates",
  "auctionhouse": "auctionhouse",
  "automod": "automod",
  "bankgui": "bankgui",
  "bankui": "bankui",
  "bedrockbreaker": "bedrockbreaker",
  "bedrockeconomy": "bedrockeconomy",
  "betterban": "betterban",
  "betterpearls": "betterpearls",
  "blocklagfix": "blocklagfix",
  "blockreplacer": "blockreplacer",
  "campfire": "campfire",
  "chestshop": "chestshop",
  "clearlag-mc": "clearlag-mc",
  "combat": "combat",
  "consumablecooldowns": "consumablecooldowns",
  "custombossbar": "custombossbar",
  "dummyitemsblocks": "dummyitemsblocks",
  "easycommandautofill": "easycommandautofill",
  "easyedit": "easyedit",
  "entitymonitor": "entitymonitor",
  "farmingchest": "farmingchest",
  "fasterprojectiles": "fasterprojectiles",
  "hypixelbow": "hypixelbow",
  "infinitebuckets": "infinitebuckets",
  "inv2chest": "inv2chest",
  "joincount": "joincount",
  "kbeditor": "kbeditor",
  "manastats": "manastats",
  "minesystem": "minesystem",
  "muteallplugin": "muteallplugin",
  "pearlteleporter": "pearlteleporter",
  "piggyoutpost": "piggyoutpost",
  "playercoords": "playercoords",
  "playergravepe": "playergravepe",
  "pocketcord": "pocketcord",
  "profanityfilter": "profanityfilter",
  "reversepositionitem": "reversepositionitem",
  "shield": "shield",
  "simplebroadcast": "simplebroadcast",
  "slapperparticlesv2": "slapperparticlesv2",
  "sponge": "sponge",
  "ultrastaffchat": "ultrastaffchat",
  "ultraluckyblocks": "ultraluckyblocks",
  "uncensoraccentedition": "uncensoraccentedition",
  "vanillaelytra": "vanillaelytra",
  "warpcore": "warpcore",
  "wft": "wft",
  "advancedbounty": "advancedbounty",
  "adventcalendar": "adventcalendar",
  "anti-interrupt": "anti-interrupt",
  "antibadpackets": "antibadpackets",
  "askyblock": "askyblock",
  "autoannouncer": "autoannouncer",
  "blazinfly": "blazinfly",
  "blazinjump": "blazinjump",
  "buildreset": "buildreset",
  "chatcooldown": "chatcooldown",
  "chatthin": "chatthin",
  "consoleexporter": "consoleexporter",
  "customelevator": "customelevator",
  "customfurnacerecipes": "customfurnacerecipes",
  "custompanels": "custompanels",
  "doorbell": "doorbell",
  "dummyenchantments": "dummyenchantments",
  "handglider": "handglider",
  "humannpc": "humannpc",
  "ignorecase": "ignorecase",
  "keyshop": "keyshop",
  "killentity": "killentity",
  "lobbyitems": "lobbyitems",
  "lootbox": "lootbox",
  "luckypouches": "luckypouches",
  "lunarranks": "lunarranks",
  "minerware": "minerware",
  "nativespectator": "nativespectator",
  "netherreactor": "netherreactor",
  "obsidianbreakertnt": "obsidianbreakertnt",
  "oh-my-pmmp": "oh-my-pmmp",
  "personaskin": "personaskin",
  "pingview": "pingview",
  "playedtime": "playedtime",
  "playerwarpsui": "playerwarpsui",
  "randomteleport": "randomteleport",
  "rankshopgui": "rankshopgui",
  "redstonedrop": "redstonedrop",
  "shulkerdye": "shulkerdye",
  "silkpickblock": "silkpickblock",
  "smeltingaccelerator": "smeltingaccelerator",
  "thespawn": "thespawn",
  "commandspy": "commandspy",
  "unclaimfinder": "unclaimfinder",
  "warzoneenvoys": "warzoneenvoys",
  "addfoodsmods": "addfoodsmods",
  "autochangetool": "autochangetool",
  "azeconomy": "azeconomy",
  "bedcoreprotect": "bedcoreprotect",
  "blockbreaker": "blockbreaker",
  "broadsword": "broadsword",
  "butils": "butils",
  "chatbridge": "chatbridge",
  "chatgames": "chatgames",
  "cmdsnooper": "cmdsnooper",
  "coppervanillamods": "coppervanillamods",
  "cropgrowth": "cropgrowth",
  "deathrunes": "deathrunes",
  "disableenchantingtable": "disableenchantingtable",
  "doubleenderchest": "doubleenderchest",
  "fakepearl": "fakepearl",
  "farmchest": "farmchest",
  "effectfood": "effectfood",
  "goldenapplecooldown": "goldenapplecooldown",
  "glasspain": "glasspain",
  "hammeracm": "hammeracm",
  "hypixelbook": "hypixelbook",
  "knockbackffa": "knockbackffa",
  "leafdecay": "leafdecay",
  "lytraaccessory": "lytraaccessory",
  "mcpetodiscord": "mcpetodiscord",
  "minibosses": "minibosses",
  "nobedrockbridging": "nobedrockbridging",
  "nochatconsole": "nochatconsole",
  "pocketradio": "pocketradio",
  "simplerandomore": "simplerandomore",
  "ranksystemvoucher": "ranksystemvoucher",
  "scorehud": "scorehud",
  "sellwand": "sellwand",
  "skyblock": "skyblock",
  "skyblockgb": "skyblockgb",
  "tpall-pm4": "tpall-pm4",
  "vbasket": "vbasket",
  "vipkeys": "vipkeys",
  "vminingsack": "vminingsack",
  "votestreak": "votestreak",
  "warpcommand": "warpcommand",
  "worldheightlimit": "worldheightlimit",
  "zelu-armoreffect": "zelu-armoreffect",
  "anticombatlog": "anticombatlog",
  "autodisableworlds": "autodisableworlds",
  "_newblazinfly": "newblazinfly",
  "blesscommand": "blesscommand",
  "chathijacker": "chathijacker",
  "commandblocker": "commandblocker",
  "complexupgradeui": "complexupgradeui",
  "customscore": "customscore",
  "fancyplayercount": "fancyplayercount",
  "frankspiggyfaction": "frankspiggyfaction",
  "godcommand": "godcommand",
  "hardcore": "hardcore",
  "kygekjoinui": "kygekjoinui",
  "kygekranksui": "kygekranksui",
  "kygekrulesui": "kygekrulesui",
  "kygektagsshop": "kygektagsshop",
  "kygekwhitelistkick": "kygekwhitelistkick",
  "levellimiter": "levellimiter",
  "luckyplayer": "luckyplayer",
  "maintenancemode": "maintenancemode",
  "mineparty": "mineparty",
  "nospace": "nospace",
  "nodropspe": "nodropspe",
  "onlyonebiome": "onlyonebiome",
  "findplayers": "findplayers",
  "playerstatus": "playerstatus",
  "profile-ui": "profile-ui",
  "servertools": "servertools",
  "shopkeepers": "shopkeepers",
  "slapperparticles": "slapperparticles",
  "superarmor": "superarmor",
  "tgcapes": "tgcapes",
  "topvoter": "topvoter",
  "voteparty": "voteparty",
  "xcoords": "xcoords",
  "xgamemode": "xgamemode",
  "xnonickspace": "xnonickspace",
  "xpshop": "xpshop",
  "antihunger": "antihunger",
  "antivoidfast": "antivoidfast",
  "antivoid-pm5": "antivoid-pm5",
  "bancommands": "bancommands",
  "betterflight": "betterflight",
  "betterhomes": "betterhomes",
  "betterwarps": "betterwarps",
  "blockblocker": "blockblocker",
  "chatradius": "chatradius",
  "crawling": "crawling",
  "customitemloader": "customitemloader",
  "customjoinsound": "customjoinsound",
  "customtools": "customtools",
  "easyannouncement": "easyannouncement",
  "easybrag": "easybrag",
  "friendssystem": "friendssystem",
  "headsortails": "headsortails",
  "killdeathsound": "killdeathsound",
  "launchacm": "launchacm",
  "lightningdeath": "lightningdeath",
  "magicstick": "magicstick",
  "minereset38": "minereset38",
  "muteall": "muteall",
  "navicompass": "navicompass",
  "noeats": "noeats",
  "nosprint": "nosprint",
  "novoid": "novoid",
  "oneplayersleep": "oneplayersleep",
  "onlineui": "onlineui",
  "piggyfactions": "piggyfactions",
  "playerscale": "playerscale",
  "playerselectors": "playerselectors",
  "playervaults": "playervaults",
  "politeteleports": "politeteleports",
  "portablecrates": "portablecrates",
  "pvpmanager": "pvpmanager",
  "randomjoinnickname": "randomjoinnickname",
  "remoteconsole": "remoteconsole",
  "shortsneak": "shortsneak",
  "simplemotd": "simplemotd",
  "skyblockspm": "skyblockspm",
  "stackstorage": "stackstorage",
  "stories": "stories",
  "superitemsshop": "superitemsshop",
  "tellraw": "tellraw",
  "s-thebridge": "s-thebridge",
  "timecommander": "timecommander",
  "transferme": "transferme",
  "trashcommand": "trashcommand",
  "vjesusbucket": "vjesusbucket",
  "vouchers": "vouchers",
  "whitelistkick": "whitelistkick",
  "worldsloader": "worldsloader",
  "actualantixray": "actualantixray",
  "advancedeaths": "advancedeaths",
  "advancedrules": "advancedrules",
  "autoinventory": "autoinventory",
  "besttools": "besttools",
  "bettercapes": "bettercapes",
  "cb-heads": "cb-heads",
  "chestkits": "chestkits",
  "clearchat": "clearchat",
  "dropprotection": "dropprotection",
  "easydoor": "easydoor",
  "elevator_block": "elevator-block",
  "epiccustomalerts": "epiccustomalerts",
  "fishingrod": "fishingrod",
  "floatingmessage": "floatingmessage",
  "freezeui": "freezeui",
  "gamemodeui": "gamemodeui",
  "grapplinghook": "grapplinghook",
  "groupjoin": "groupjoin",
  "hivecorruptor": "hivecorruptor",
  "imageonmap": "imageonmap",
  "itemrenametag": "itemrenametag",
  "kdr2": "kdr2",
  "keepinventory": "keepinventory",
  "lockeditem": "lockeditem",
  "maxenchants": "maxenchants",
  "mobs": "mobs",
  "noflyworld": "noflyworld",
  "pixelbloodpe": "pixelbloodpe",
  "sakuraspawners": "sakuraspawners",
  "customshopui": "customshopui",
  "slapper": "slapper",
  "sudo": "sudo",
  "taptodo": "taptodo",
  "therankshop": "therankshop",
  "tr-booknotice": "tr-booknotice",
  "ultra-repair": "ultra-repair",
  "vanillaec": "vanillaec",
  "vanillafortune": "vanillafortune",
  "vanillahopper": "vanillahopper",
  "vanillaxp": "vanillaxp",
  "vclearchat": "vclearchat",
  "voicecraft": "voicecraft",
  "vpickaxe": "vpickaxe",
  "weather": "weather",
  "worldguardian": "worldguardian",
  "fixvalidationxuid": "fixvalidationxuid",
  "acidisland": "acidisland",
  "adminlogin": "adminlogin",
  "bettermute": "bettermute",
  "blockdatarecorder": "blockdatarecorder",
  "buildertools": "buildertools",
  "c20s-actions": "c20s-actions",
  "c20s-tpall": "c20s-tpall",
  "changedisplayname": "changedisplayname",
  "chat-filter": "chat-filter",
  "chatperworld": "chatperworld",
  "commanddisabler": "commanddisabler",
  "commandpermissionmessage": "commandpermissionmessage",
  "relics": "relics",
  "customcraft": "customcraft",
  "dailystats": "dailystats",
  "healandfeed": "healandfeed",
  "healthtag": "healthtag",
  "itemfactory": "itemfactory",
  "itemsender": "itemsender",
  "mineflow": "mineflow",
  "noemotemessage": "noemotemessage",
  "nofarmlanddecay": "nofarmlanddecay",
  "oceanite": "oceanite",
  "offlineplayertp": "offlineplayertp",
  "oneblock": "oneblock",
  "personaadapter": "personaadapter",
  "pluginmanager": "pluginmanager",
  "regionprotect": "regionprotect",
  "report": "report",
  "rewards": "rewards",
  "rulesbook": "rulesbook",
  "skinthief": "skinthief",
  "spyglass-sniper": "spyglass-sniper",
  "socialspy": "socialspy",
  "soupffa": "soupffa",
  "stalker": "stalker",
  "staminasystem": "staminasystem",
  "starterkit": "starterkit",
  "trash_can": "trash-can",
  "worldtime": "worldtime",
  "alwaysday": "alwaysday",
  "antiexplosions": "antiexplosions",
  "antifalldamage": "antifalldamage",
  "antiinstabreak": "antiinstabreak",
  "antiserverstop": "antiserverstop",
  "antitramplefarmland": "antitramplefarmland",
  "antixraype": "antixraype",
  "asyncworldreset": "asyncworldreset",
  "autosmeltore": "autosmeltore",
  "basicspawnprotection": "basicspawnprotection",
  "betterbroadcast": "betterbroadcast",
  "bettercancel": "bettercancel",
  "blockgenerator": "blockgenerator",
  "blocksoundspm": "blocksoundspm",
  "bulklayereditor": "bulklayereditor",
  "chatclearpe": "chatclearpe",
  "cmdscheduler": "cmdscheduler",
  "crashbanusers": "crashbanusers",
  "cropsxp": "cropsxp",
  "custombow": "custombow",
  "customitemcmd": "customitemcmd",
  "datacleaner": "datacleaner",
  "deathchestpro": "deathchestpro",
  "deathparticle": "deathparticle",
  "deviceblockerpm": "deviceblockerpm",
  "devilmode": "devilmode",
  "extendedblocksconverter": "extendedblocksconverter",
  "ezchatmod": "ezchatmod",
  "fkickall": "fkickall",
  "guardianjoin": "guardianjoin",
  "hacks": "hacks",
  "healthlimit": "healthlimit",
  "hitparticle": "hitparticle",
  "inventorykeepchance": "inventorykeepchance",
  "itemdroptext": "itemdroptext",
  "keepexp": "keepexp",
  "nicknames": "nicknames",
  "nightvision": "nightvision",
  "noadvertisings": "noadvertisings",
  "nochangeskin": "nochangeskin",
  "nocraftitem": "nocraftitem",
  "oneblockscore": "oneblockscore",
  "oplist": "oplist",
  "perworldplayer": "perworldplayer",
  "portablecrafting": "portablecrafting",
  "rconserver": "rconserver",
  "renameitems": "renameitems",
  "signit": "signit",
  "simplefly": "simplefly",
  "simplehubdelay": "simplehubdelay",
  "simplereplies": "simplereplies",
  "slapperhitsound": "slapperhitsound",
  "spectrezone": "spectrezone",
  "spider": "spider",
  "textreplacer": "textreplacer",
  "track": "track",
  "tracker": "tracker",
  "vanillaknockback": "vanillaknockback",
  "wilderness": "wilderness",
  "antiblock": "antiblock",
  "antidecay": "antidecay",
  "antiinterupt": "antiinterupt",
  "antinuker": "antinuker",
  "bardai": "bardai",
  "blockme": "blockme",
  "bossbar": "bossbar",
  "breakwarn": "breakwarn",
  "craftmanager": "craftmanager",
  "ghost": "ghost",
  "inether": "inether",
  "mineflowmoreactions": "mineflowmoreactions",
  "piggycustomenchants": "piggycustomenchants",
  "piggyshopui": "piggyshopui",
  "pmgpt": "pmgpt",
  "purechat": "purechat",
  "redstonecircuit": "redstonecircuit",
  "spyglass": "spyglass",
  "tpbow": "tpbow",
  "vegahcfelevator": "vegahcfelevator",
  "vegaleaderboards": "vegaleaderboards",
  "vegatouchpot": "vegatouchpot",
  "aboutme": "aboutme",
  "creditsflip": "creditsflip",
  "customlevelkb": "customlevelkb",
  "emojispro": "emojispro",
  "emoteannounce": "emoteannounce",
  "everyonesaywhat": "everyonesaywhat",
  "hostinfogetter": "hostinfogetter",
  "joinstreak": "joinstreak",
  "livexyz": "livexyz",
  "mcpetoconsole": "mcpetoconsole",
  "nativedimensions": "nativedimensions",
  "piggyauctions": "piggyauctions",
  "piggycrates": "piggycrates",
  "pvpshop": "pvpshop",
  "snowmod": "snowmod",
  "specialwalk": "specialwalk",
  "swapball": "swapball",
  "thebridges": "thebridges",
  "tpall": "tpall",
  "tyho": "tyho",
  "votekick": "votekick",
  "flyspeed": "flyspeed",
  "worldprotect": "worldprotect",
  "xboxprofile": "xboxprofile",
  "atm": "atm",
  "buildbattle": "buildbattle",
  "clearlag": "clearlag",
  "customvanillaenchants": "customvanillaenchants",
  "easywarps": "easywarps",
  "forminteractionfix": "forminteractionfix",
  "godmod": "godmod",
  "myplot": "myplot",
  "safercon": "safercon",
  "simplelay": "simplelay",
  "simplenpc": "simplenpc",
  "sitwands": "sitwands",
  "suggestions": "suggestions",
  "swordmodded": "swordmodded",
  "tnttag": "tnttag",
  "pm-trident": "pm-trident",
  "birthdayspe": "birthdayspe",
  "craftingplus": "craftingplus",
  "creditsscore": "creditsscore",
  "datacleaning": "datacleaning",
  "deathhead": "deathhead",
  "economycshop": "economycshop",
  "freedom": "freedom",
  "funblockoneblock": "funblockoneblock",
  "getping": "getping",
  "globaltoast": "globaltoast",
  "nickui": "nickui",
  "nobacksprint": "nobacksprint",
  "wparkour": "wparkour",
  "parties": "parties",
  "phqx-client": "phqx-client",
  "simplespawns": "simplespawns",
  "worldinventory": "worldinventory",
  "antiafk": "antiafk",
  "antibotbe": "antibotbe",
  "autosprint": "autosprint",
  "calculatoracm": "calculatoracm",
  "cskull": "cskull",
  "customitemapi": "customitemapi",
  "easywing": "easywing",
  "emojiattack": "emojiattack",
  "iland": "iland",
  "joincommand": "joincommand",
  "kygekpingtps": "kygekpingtps",
  "movecommand": "movecommand",
  "nospectatorhitsound": "nospectatorhitsound",
  "randomtp": "randomtp",
  "reports": "reports",
  "toastbroadcaster": "toastbroadcaster",
  "worldguard": "worldguard",
  "1vs1": "1vs1",
  "1vs1-pm4": "1vs1-pm4",
  "advanceditem": "advanceditem",
  "bmpingtag": "bmpingtag",
  "cps": "cps",
  "economyrename": "economyrename",
  "freezesystem": "freezesystem",
  "groupsapi": "groupsapi",
  "invisibleskinblocker": "invisibleskinblocker",
  "nbteditor": "nbteditor",
  "no4dskins": "no4dskins",
  "playergrave": "playergrave",
  "pmjellylegs": "pmjellylegs",
  "sellme": "sellme",
  "simplejoinmessage": "simplejoinmessage",
  "slapbackv2": "slapbackv2",
  "slappercooldownv2": "slappercooldownv2",
  "slapperrotationv2": "slapperrotationv2",
  "thebridge": "thebridge",
  "tpallplayers": "tpallplayers",
  "bottlexp": "bottlexp",
  "areaguard-hiroteam": "areaguard-hiroteam",
  "blocksniper": "blocksniper",
  "commandlogger": "commandlogger",
  "errorlog": "errorlog",
  "headshotsound": "headshotsound",
  "itembrag": "itembrag",
  "launchpad": "launchpad",
  "loadallworlds": "loadallworlds",
  "loadeveryworlds": "loadeveryworlds",
  "multiplayercounter": "multiplayercounter",
  "nofly": "nofly",
  "nopvp": "nopvp",
  "seasonshop": "seasonshop",
  "tempban": "tempban",
  "vecnaleaderboards": "vecnaleaderboards",
  "worldborder": "worldborder",
  "worldwhitelist": "worldwhitelist",
  "autopickup": "autopickup",
  "banitem-pm4": "banitem-pm4",
  "capeslocker": "capeslocker",
  "coin-flip": "coin-flip",
  "combatlogger": "combatlogger",
  "factionmaster": "factionmaster",
  "factionmasteradmintools": "factionmasteradmintools",
  "factionmasterinvitationimprove": "factionmasterinvitationimprove",
  "footjob-pm4": "footjob-pm4",
  "iprotector-pm4": "iprotector-pm4",
  "itemlifetime": "itemlifetime",
  "itemutils": "itemutils",
  "netherite": "netherite",
  "nosleep": "nosleep",
  "paidall": "paidall",
  "pearlcooldownpro": "pearlcooldownpro",
  "pizzaplug": "pizzaplug",
  "pureperms": "pureperms",
  "purepermsscore": "purepermsscore",
  "reviveplus": "reviveplus",
  "saywelcome": "saywelcome",
  "sellstick": "sellstick",
  "snowball": "snowball",
  "totemjoin": "totemjoin",
  "trashcanplus": "trashcanplus",
  "voting38": "voting38",
  "announce": "announce",
  "bloodinmc": "bloodinmc",
  "capital": "capital",
  "commandmaj": "commandmaj",
  "createdelcraft-hiroteam": "createdelcraft-hiroteam",
  "custommessages": "custommessages",
  "deathposition": "deathposition",
  "ecoapiscore": "ecoapiscore",
  "elevator": "elevator",
  "elevatorspm4": "elevatorspm4",
  "emotesimple": "emotesimple",
  "infotag": "infotag",
  "is_": "is",
  "launchabletnt": "launchabletnt",
  "mentionedmessage": "mentionedmessage",
  "nicknamecolors": "nicknamecolors",
  "nocraft": "nocraft",
  "nuke": "nuke",
  "pockit": "pockit",
  "protectyourspawn": "protectyourspawn",
  "tntexplodetime": "tntexplodetime",
  "viriontools": "viriontools",
  "whalealert": "whalealert",
  "adminprotect": "adminprotect",
  "bless": "bless",
  "blockcommands": "blockcommands",
  "chatrange": "chatrange",
  "crossbow": "crossbow",
  "customcraftdraz": "customcraftdraz",
  "deathmoney": "deathmoney",
  "disguise": "disguise",
  "effectsee": "effectsee",
  "emotecommands": "emotecommands",
  "inventoryshards": "inventoryshards",
  "hangglider-hiroteam": "hangglider-hiroteam",
  "helpbook": "helpbook",
  "infoapi": "infoapi",
  "pecollide": "pecollide",
  "playcommand": "playcommand",
  "playtime": "playtime",
  "rgb": "rgb",
  "royalpingtag": "royalpingtag",
  "skinban": "skinban",
  "slappercooldown": "slappercooldown",
  "viewdistance": "viewdistance",
  "xpbottle": "xpbottle",
  "yourinformation": "yourinformation",
  "advancekillmoney": "advancekillmoney",
  "alwaysspawn": "alwaysspawn",
  "aquaman": "aquaman",
  "captchaverification": "captchaverification",
  "chatrewardevent": "chatrewardevent",
  "commandsexploder": "commandsexploder",
  "dynamitepala": "dynamitepala",
  "economyapi": "economyapi",
  "football": "football",
  "hotbar": "hotbar",
  "jailmate": "jailmate",
  "kygeklastposition": "kygeklastposition",
  "lobbyplayerlimit": "lobbyplayerlimit",
  "palermotown": "palermotown",
  "pignotify": "pignotify",
  "pingkick": "pingkick",
  "plotrate": "plotrate",
  "premiumcase": "premiumcase",
  "reportsystem": "reportsystem",
  "showperms": "showperms",
  "simplecustomcraft": "simplecustomcraft",
  "simplestaffchat": "simplestaffchat",
  "worldteleportui": "worldteleportui",
  "advancedinstantrespawn": "advancedinstantrespawn",
  "antiframeedit": "antiframeedit",
  "antivoid": "antivoid",
  "composter": "composter",
  "crashtransfer": "crashtransfer",
  "credits": "credits",
  "advancedfurnace": "advancedfurnace",
  "devirion": "devirion",
  "endercooldown": "endercooldown",
  "lessismore": "lessismore",
  "mentionsound": "mentionsound",
  "multiversion": "multiversion",
  "onesleeper": "onesleeper",
  "oregen": "oregen",
  "pingmanager": "pingmanager",
  "playertags": "playertags",
  "rankeasy": "rankeasy",
  "simplefeed": "simplefeed",
  "simpleheal": "simpleheal",
  "simplehome": "simplehome",
  "snow": "snow",
  "wordscrambler": "wordscrambler",
  "announcesmodifier": "announcesmodifier",
  "antiglitch": "antiglitch",
  "bedwars": "bedwars",
  "coinsflipui": "coinsflipui",
  "customnpc": "customnpc",
  "easykits": "easykits",
  "easymoderation": "easymoderation",
  "emojis": "emojis",
  "extendedblocks": "extendedblocks",
  "factionmasterbank": "factionmasterbank",
  "floatingtextcreator": "floatingtextcreator",
  "itemsmagnet": "itemsmagnet",
  "maxkoth": "maxkoth",
  "magicwe2": "magicwe2",
  "offhand": "offhand",
  "perworldplayerslist": "perworldplayerslist",
  "plothomes": "plothomes",
  "ptimeui": "ptimeui",
  "ratio": "ratio",
  "simplemaprenderer": "simplemaprenderer",
  "slapback": "slapback",
  "slapperrotation": "slapperrotation",
  "spongebobmeme": "spongebobmeme",
  "staffmode": "staffmode",
  "vanillacoordinates": "vanillacoordinates",
  "vehicles": "vehicles",
  "welcome": "welcome",
  "boilingcauldrons": "boilingcauldrons",
  "burgerspawners": "burgerspawners",
  "ding": "ding",
  "fertilizerparticles": "fertilizerparticles",
  "laggerremover": "laggerremover",
  "ourinventory": "ourinventory",
  "pigtranslate": "pigtranslate",
  "shareditemsandcoords": "shareditemsandcoords",
  "simplefaction": "simplefaction",
  "simplepets": "simplepets",
  "statsx": "statsx",
  "armorvalue": "armorvalue",
  "blocksconverter": "blocksconverter",
  "bowcooldown": "bowcooldown",
  "burgercustomarmor": "burgercustomarmor",
  "burgermorphs": "burgermorphs",
  "customvoidlevel": "customvoidlevel",
  "furnacecommand": "furnacecommand",
  "infobook": "infobook",
  "itemdisplay": "itemdisplay",
  "kygekeatheal": "kygekeatheal",
  "otroll": "otroll",
  "packetlimiter": "packetlimiter",
  "poopcraft": "poopcraft",
  "scoreboard": "scoreboard",
  "admintrollv2": "admintrollv2",
  "antiaurabot": "antiaurabot",
  "armoreffect": "armoreffect",
  "autosmelt": "autosmelt",
  "basicscore": "basicscore",
  "blockhunt": "blockhunt",
  "chatlevel": "chatlevel",
  "complexpets": "complexpets",
  "customitem": "customitem",
  "dynamicft": "dynamicft",
  "fightpopup": "fightpopup",
  "foodeffect": "foodeffect",
  "functionpacks": "functionpacks",
  "godmode": "godmode",
  "grantgui": "grantgui",
  "itemspawners": "itemspawners",
  "mcpediscordrelay": "mcpediscordrelay",
  "notmexboxliveauth": "notmexboxliveauth",
  "onlinetime": "onlinetime",
  "orespawners": "orespawners",
  "randomore": "randomore",
  "signtodiscord": "signtodiscord",
  "stickeffect": "stickeffect",
  "tagmessages": "tagmessages",
  "thefloorislava": "thefloorislava",
  "touchlight": "touchlight",
  "traps": "traps",
  "treecapitator": "treecapitator",
  "treechopper": "treechopper",
  "workersdemo": "workersdemo",
  "antixray": "antixray",
  "atenchants": "atenchants",
  "boostblock": "boostblock",
  "commandeditor": "commandeditor",
  "commandfix": "commandfix",
  "deatheffect": "deatheffect",
  "elevatorblock": "elevatorblock",
  "formcreator": "formcreator",
  "giveawayplugin": "giveawayplugin",
  "kygekfarmlanddecay": "kygekfarmlanddecay",
  "manhunt": "manhunt",
  "minerafurnace": "minerafurnace",
  "playerban": "playerban",
  "pm-beacons": "pm-beacons",
  "redskyblock": "redskyblock",
  "replay": "replay",
  "stairseat": "stairseat",
  "vanillablocks": "vanillablocks",
  "achievementreward": "achievementreward",
  "chatfx": "chatfx",
  "chorusplant": "chorusplant",
  "colorparticle": "colorparticle",
  "complexcrates": "complexcrates",
  "craftpermission": "craftpermission",
  "customdrop": "customdrop",
  "gravity": "gravity",
  "hammer": "hammer",
  "itemid": "itemid",
  "joinskinsave": "joinskinsave",
  "keepyourxp": "keepyourxp",
  "mission": "mission",
  "moneyui": "moneyui",
  "playertrade": "playertrade",
  "pocketvote": "pocketvote",
  "prisons": "prisons",
  "robotverification": "robotverification",
  "scoreboardspe": "scoreboardspe",
  "slimeboost": "slimeboost",
  "slotsplus": "slotsplus",
  "trident": "trident",
  "whitelistmessage": "whitelistmessage",
  "anticraft": "anticraft",
  "betterblockpick": "betterblockpick",
  "combatscore": "combatscore",
  "customcrafting": "customcrafting",
  "easytp": "easytp",
  "factionspe": "factionspe",
  "friends": "friends",
  "graves": "graves",
  "ignoreplayer": "ignoreplayer",
  "customjoinmessage": "customjoinmessage",
  "mywarp": "mywarp",
  "oneblockafk": "oneblockafk",
  "payall": "payall",
  "pcfly": "pcfly",
  "pureentitiesx": "pureentitiesx",
  "simplebanner": "simplebanner",
  "souppvp": "souppvp",
  "stoplag": "stoplag",
  "autosell": "autosell",
  "buykeepinv": "buykeepinv",
  "chestrefill": "chestrefill",
  "coinssystem": "coinssystem",
  "drawer-hiroteam": "drawer-hiroteam",
  "droplog": "droplog",
  "genui": "genui",
  "giftpackage": "giftpackage",
  "interacteffects": "interacteffects",
  "itemcooldowns": "itemcooldowns",
  "nofood": "nofood",
  "pvptoggle": "pvptoggle",
  "randomdrops": "randomdrops",
  "rank.up": "rank-up",
  "recurring-message": "recurring-message",
  "sellxp": "sellxp",
  "stargate-atlantis": "stargate-atlantis",
  "thorhammer": "thorhammer",
  "trashcan": "trashcan",
  "werbung-pmmp": "werbung-pmmp",
  "allclaimplotcommand": "allclaimplotcommand",
  "burgeraliasmanager": "burgeraliasmanager",
  "captcha": "captcha",
  "dancingfarm": "dancingfarm",
  "doemote": "doemote",
  "errorlogger": "errorlogger",
  "executeit": "executeit",
  "fakeplayers": "fakeplayers",
  "flype": "flype",
  "hidenametag": "hidenametag",
  "itemfilter": "itemfilter",
  "keepinventorype": "keepinventorype",
  "masks": "masks",
  "mockingbird": "mockingbird",
  "nichijoinlocation": "nichijoinlocation",
  "nichiwikipmmp": "nichiwikipmmp",
  "plotrating": "plotrating",
  "pm-shulkerboxes": "pm-shulkerboxes",
  "randomspawns": "randomspawns",
  "ranks": "ranks",
  "realtime": "realtime",
  "safeserver-hiroteam": "safeserver-hiroteam",
  "simplecape": "simplecape",
  "simplesleep": "simplesleep",
  "thewarn": "thewarn",
  "vanillapickblock": "vanillapickblock",
  "antinostuffarea-hiroteam": "antinostuffarea-hiroteam",
  "backupme": "backupme",
  "baninformation": "baninformation",
  "block-generators": "block-generators",
  "bloodfx": "bloodfx",
  "cucumber": "cucumber",
  "customdrop-hiroteam": "customdrop-hiroteam",
  "decorations": "decorations",
  "easyrepairitems": "easyrepairitems",
  "extinguish": "extinguish",
  "falloutinventoryclear": "falloutinventoryclear",
  "headhunter": "headhunter",
  "kickall": "kickall",
  "minion": "minion",
  "pemmo": "pemmo",
  "pingsystem": "pingsystem",
  "pluginverifytool": "pluginverifytool",
  "pvpmessages": "pvpmessages",
  "randommotd": "randommotd",
  "redrover": "redrover",
  "signtodos": "signtodos",
  "spawncmd": "spawncmd",
  "staffstatus": "staffstatus",
  "addnetherite-hiroteam": "addnetherite-hiroteam",
  "autoclearchat": "autoclearchat",
  "bettervoting": "bettervoting",
  "blocksounds": "blocksounds",
  "bravoclan": "bravoclan",
  "emotes": "emotes",
  "footjob": "footjob",
  "groupsui": "groupsui",
  "hubdelay": "hubdelay",
  "jobui": "jobui",
  "keepinv": "keepinv",
  "status": "status",
  "ranktext": "ranktext",
  "specter": "specter",
  "tacokbmodifier": "tacokbmodifier",
  "titancommandblocker": "titancommandblocker",
  "xgtantixray": "xgtantixray",
  "antihack": "antihack",
  "bin": "bin",
  "blockitemframe-hiroteam": "blockitemframe-hiroteam",
  "burgertimezones": "burgertimezones",
  "c4-hiroteam": "c4-hiroteam",
  "coinflip": "coinflip",
  "slapperplayercount": "slapperplayercount",
  "customfurnace": "customfurnace",
  "effectblock-hiroteam": "effectblock-hiroteam",
  "enderchestslots": "enderchestslots",
  "exchange-hiroteam": "exchange-hiroteam",
  "foodeffects": "foodeffects",
  "notesui": "notesui",
  "pcebookshop": "pcebookshop",
  "piggycustomenchantsshop": "piggycustomenchantsshop",
  "resourcepacktoolsplugin": "resourcepacktoolsplugin",
  "spinningcoin": "spinningcoin",
  "telegrampm": "telegrampm",
  "triggerpe": "triggerpe",
  "worldplayercount": "worldplayercount",
  "xp": "xp",
  "advancedjobs": "advancedjobs",
  "arrowtrails": "arrowtrails",
  "autoclearlagg": "autoclearlagg",
  "blazinjoin": "blazinjoin",
  "chatmuffler": "chatmuffler",
  "colormessage": "colormessage",
  "cpspopup": "cpspopup",
  "cpstag": "cpstag",
  "customtell": "customtell",
  "dragons": "dragons",
  "easyhomes": "easyhomes",
  "easyhomesteleportwarmup": "easyhomesteleportwarmup",
  "enchantui": "enchantui",
  "gomoku": "gomoku",
  "gotifynotifications": "gotifynotifications",
  "itemstylus": "itemstylus",
  "killstreak": "killstreak",
  "myentities": "myentities",
  "mysterycrate": "mysterycrate",
  "nodrop": "nodrop",
  "novpn": "novpn",
  "pceallychecks": "pceallychecks",
  "pceeasyenchants": "pceeasyenchants",
  "rgbarmor": "rgbarmor",
  "rgbeacon": "rgbeacon",
  "scoretag": "scoretag",
  "admintroll": "admintroll",
  "armoureffects": "armoureffects",
  "backpack": "backpack",
  "bossannouncement": "bossannouncement",
  "bossplugin": "bossplugin",
  "burgerlootprotection": "burgerlootprotection",
  "vaultchest": "vaultchest",
  "ec-tableui": "ec-tableui",
  "firecracker": "firecracker",
  "gameeventplugin": "gameeventplugin",
  "itemframecommands": "itemframecommands",
  "kitsplus": "kitsplus",
  "mailplugin": "mailplugin",
  "makemeadmin": "makemeadmin",
  "market": "market",
  "playeradmin": "playeradmin",
  "playerinfo": "playerinfo",
  "questplugin": "questplugin",
  "burgersellwands": "burgersellwands",
  "sponges": "sponges",
  "taptopot": "taptopot",
  "tntblastmodifier": "tntblastmodifier",
  "warpui": "warpui",
  "worldlimits": "worldlimits",
  "advancedkits": "advancedkits",
  "autoexp": "autoexp",
  "festival": "festival",
  "inventorysynchronizer": "inventorysynchronizer",
  "killhealth": "killhealth",
  "morphx": "morphx",
  "multiservercounter": "multiservercounter",
  "nanocombinergui": "nanocombinergui",
  "personatoskin": "personatoskin",
  "playerskinstealer": "playerskinstealer",
  "skywars": "skywars",
  "taptoarmor": "taptoarmor",
  "advancedmock": "advancedmock",
  "bounty": "bounty",
  "creativelimit": "creativelimit",
  "deviceblocker": "deviceblocker",
  "economypshop": "economypshop",
  "economysell": "economysell",
  "economyshop": "economyshop",
  "enderpearlcooldown": "enderpearlcooldown",
  "extragl": "extragl",
  "filterx": "filterx",
  "globalmute": "globalmute",
  "gungame": "gungame",
  "itemcase": "itemcase",
  "kitui": "kitui",
  "koth": "koth",
  "lockmystuff": "lockmystuff",
  "mapimageengine": "mapimageengine",
  "multieconomy": "multieconomy",
  "naps": "naps",
  "pocketdockconsole": "pocketdockconsole",
  "skywars-reward": "skywars-reward",
  "tempranks": "tempranks",
  "weapons": "weapons",
  "whatcrates": "whatcrates",
  "advancedjoin": "advancedjoin",
  "banknotes": "banknotes",
  "blazinhud": "blazinhud",
  "blazinsigns": "blazinsigns",
  "blazinvanish": "blazinvanish",
  "classiclightningstrike": "classiclightningstrike",
  "clikactions": "clikactions",
  "crashlogger": "crashlogger",
  "customquery": "customquery",
  "floatinghotbar": "floatinghotbar",
  "freeze": "freeze",
  "gapplecooldown": "gapplecooldown",
  "iprotector": "iprotector",
  "mobstacker": "mobstacker",
  "multiport": "multiport",
  "pingtag": "pingtag",
  "sizeplayer": "sizeplayer",
  "slashskin": "slashskin",
  "statscraft": "statscraft",
  "veinminer": "veinminer",
  "warpspro": "warpspro",
  "whattheserver": "whattheserver",
  "worldloader": "worldloader",
  "worldreset": "worldreset",
  "buycraftpm": "buycraftpm",
  "byteme": "byteme",
  "chestfinder": "chestfinder",
  "crashfixer": "crashfixer",
  "customerrormessage": "customerrormessage",
  "essentialstp": "essentialstp",
  "eventcommands": "eventcommands",
  "imageconverter": "imageconverter",
  "jukebox": "jukebox",
  "luckyblock": "luckyblock",
  "miningrewards": "miningrewards",
  "namespaceremover": "namespaceremover",
  "oreearn": "oreearn",
  "playerwarps": "playerwarps",
  "powertools": "powertools",
  "sellall": "sellall",
  "uncensor": "uncensor",
  "8ball": "8ball",
  "aimtp": "aimtp",
  "antiantiswearfilter": "antiantiswearfilter",
  "antienchantmentabuse": "antienchantmentabuse",
  "authui": "authui",
  "autoxp": "autoxp",
  "chatfilter": "chatfilter",
  "custombooks": "custombooks",
  "drops": "drops",
  "geoblock": "geoblock",
  "informationx": "informationx",
  "moveui": "moveui",
  "netban": "netban",
  "newspaper": "newspaper",
  "piggytutorials": "piggytutorials",
  "pocketislands": "pocketislands",
  "pocketlotto": "pocketlotto",
  "seedevice": "seedevice",
  "simplenamecolor": "simplenamecolor",
  "viewcompass": "viewcompass",
  "autoinv": "autoinv",
  "autorestarter": "autorestarter",
  "autoupdater": "autoupdater",
  "clearplayer": "clearplayer",
  "customalerts": "customalerts",
  "everybodythonk": "everybodythonk",
  "guessthenumber": "guessthenumber",
  "hungergames": "hungergames",
  "kdr": "kdr",
  "banwarn": "banwarn",
  "manyworlds": "manyworlds",
  "minereset": "minereset",
  "nofalldamage": "nofalldamage",
  "playerhead": "playerhead",
  "purechatextras": "purechatextras",
  "restrictedskins": "restrictedskins",
  "shadowanticheat": "shadowanticheat",
  "staffchat": "staffchat",
  "tictactoe": "tictactoe",
  "timestopper": "timestopper",
  "treasurechest": "treasurechest",
  "worldtp": "worldtp",
  "antispampro": "antispampro",
  "banitem": "banitem",
  "basichud": "basichud",
  "blazinbroadcasts": "blazinbroadcasts",
  "blockeffects": "blockeffects",
  "broadcaster": "broadcaster",
  "cameraman": "cameraman",
  "capslimit": "capslimit",
  "chatcensor": "chatcensor",
  "colorfularmor": "colorfularmor",
  "compassxyz": "compassxyz",
  "economyland": "economyland",
  "eventsounds": "eventsounds",
  "fastrespawn": "fastrespawn",
  "firework": "firework",
  "gears": "gears",
  "gmpermissions": "gmpermissions",
  "grabbag": "grabbag",
  "itemcloud": "itemcloud",
  "limitheight": "limitheight",
  "linkplayercount": "linkplayercount",
  "lockit": "lockit",
  "magicteleportal": "magicteleportal",
  "mspawns": "mspawns",
  "neon": "neon",
  "nohunger": "nohunger",
  "notell": "notell",
  "notp": "notp",
  "parkour": "parkour",
  "perworldchat": "perworldchat",
  "portalspe": "portalspe",
  "profileui": "profileui",
  "rankpoints": "rankpoints",
  "repair": "repair",
  "roleplay": "roleplay",
  "serverchannels": "serverchannels",
  "sheep": "sheep",
  "signportal": "signportal",
  "simpleauthhelper": "simpleauthhelper",
  "simplewarp": "simplewarp",
  "signserverstats": "signserverstats",
  "statuslist": "statuslist",
  "timeranks": "timeranks",
  "warnoffline": "warnoffline",
  "worldbackup": "worldbackup",
  "advancedfly": "advancedfly",
  "consolepush": "consolepush",
  "discordmcpe": "discordmcpe",
  "mystats": "mystats",
  "replaysystem": "replaysystem",
  "simpleauth": "simpleauth",
  "teleportationbow": "teleportationbow",
  "timerplus": "timerplus",
  "translate": "translate",
  "worldstyler": "worldstyler",
  "alias": "alias",
  "autominereset": "autominereset",
  "blockcmd": "blockcmd",
  "economyjob": "economyjob",
  "mie_converter": "mie-converter",
  "pexprotection": "pexprotection",
  "popupalerts": "popupalerts",
  "rankup": "rankup",
  "stairseatdown": "stairseatdown",
  "vanillaenchantments": "vanillaenchantments",
  "virtualchest": "virtualchest",
  "votereward": "votereward",
  "xyz": "xyz",
  "achieve": "achieve",
  "cellpe": "cellpe",
  "chatchannel": "chatchannel",
  "custombar": "custombar",
  "economyproperty": "economyproperty",
  "fireworks": "fireworks",
  "genpainterpe": "genpainterpe",
  "jail": "jail",
  "spherable": "spherable",
  "spooky": "spooky",
  "turrets": "turrets",
  "ultravaults": "ultravaults",
  "xbl_playerlist": "xbl-playerlist",
  "2fa": "2fa",
  "explosivearrows": "explosivearrows",
  "packetlogger-po": "packetlogger-po",
  "superbar": "superbar",
  "vipslots": "vipslots",
  "chattodiscord": "chattodiscord",
  "functions": "functions",
  "killcounter": "killcounter",
  "myauth": "myauth",
  "mymoney": "mymoney",
  "piggyanticheats": "piggyanticheats",
  "piggyauth": "piggyauth",
  "simplemacros": "simplemacros",
  "vpnguard": "vpnguard",
  "anticheat": "anticheat",
  "elytra": "elytra",
  "fasttravel": "fasttravel",
  "hereauth": "hereauth",
  "megaban": "megaban",
  "crossserverpm": "crossserverpm"
}
